gh_mcp-0.3.5.dist-info/METADATA
gh_mcp-0.3.5.dist-info/WHEEL
gh_mcp-0.3.5.dist-info/entry_points.txt
gh_mcp/__main__.py
gh_mcp/impl.py
gh_mcp/utils.py
gh_mcp/yaml.py
gh_mcp-0.3.5.dist-info/RECORD
