Metadata-Version: 2.1
Name: gh-mcp
Version: 0.3.5
Summary: Refined MCP server for GitHub GraphQL API
Requires-Python: >=3.12
Requires-Dist: fastmcp<2.14.0,>=2.12.5
